LICENSE
README.md
pyproject.toml
setup.py
pydll/__init__.py
pydll/__main__.py
pydynamiclib.egg-info/PKG-INFO
pydynamiclib.egg-info/SOURCES.txt
pydynamiclib.egg-info/dependency_links.txt
pydynamiclib.egg-info/entry_points.txt
pydynamiclib.egg-info/requires.txt
pydynamiclib.egg-info/top_level.txt